{"appointments":[{"domElements":["rsCalendar_0_0"],"id":"4551O2R/PJFIV","visible":true,"subject":"Maths/Physics\\u003cbr /\\u003eSarah Rowland","timeZoneID":"","description":"(SB16) 09:30-11:15","toolTip":"Maths/Physics\\u003cbr /\\u003eSarah Rowland","recurrenceState":0,"internalID":"/wEFDTQ1NTFPMlIvUEpGSVY1ZHdIvKbfZc1ix5U1Fa+JguwMiGJRtxFG6l4K89EbaQ==","start":"2022/10/05 09:30","end":"2022/10/05 11:15"},{"domElements":["rsCalendar_1_0"],"id":"4552U7Y/Q9V5H","visible":true,"subject":"Communication\\u003cbr /\\u003eLissa Jenkins","timeZoneID":"","description":"(SB18) 11:30-12:30","toolTip":"Communication\\u003cbr /\\u003eLissa Jenkins","recurrenceState":0,"internalID":"/wEFDTQ1NTJVN1kvUTlWNUjJSMcM3z2PsPIQudiB2hkQw5QHqisLkXl4k5yGlJYquw==","start":"2022/10/05 11:30","end":"2022/10/05 12:30"},{"domElements":["rsCalendar_2_0"],"id":"4554JOP/SMEGX","visible":true,"subject":"Biology\\u003cbr /\\u003eJeremy Lewis","timeZoneID":"","description":"(SB24) 13:30-15:30","toolTip":"Biology\\u003cbr /\\u003eJeremy Lewis","recurrenceState":0,"internalID":"/wEFDTQ1NTRKT1AvU01FR1jzIgGGeQkl1V42ZIk7SkicD6JFGTyS8hrlD9OCFMM4uQ==","start":"2022/10/05 13:30","end":"2022/10/05 15:30"},{"domElements":["rsCalendar_3_0"],"id":"455514K/BEJ38","visible":true,"subject":"Tutorial\\u003cbr /\\u003eJeremy Lewis","timeZoneID":"","description":"(SB16) 09:30-10:30","toolTip":"Tutorial\\u003cbr /\\u003eJeremy Lewis","recurrenceState":0,"internalID":"/wEFDTQ1NTUxNEsvQkVKMzgRS7TpDUfH76GE7LuXq+6gB99VKu6vocjd0Pvz/Ym0xw==","start":"2022/10/06 09:30","end":"2022/10/06 10:30"},{"domElements":["rsCalendar_4_0"],"id":"4557Z3S/IBQUC","visible":true,"subject":"Maths/Physics\\u003cbr /\\u003eSarah Rowland","timeZoneID":"","description":"(SB16) 10:45-12:30","toolTip":"Maths/Physics\\u003cbr /\\u003eSarah Rowland","recurrenceState":0,"internalID":"/wEFDTQ1NTdaM1MvSUJRVUMwcZv+aVAIuOTAbQh8oUanW3UgiPMFKcIHbfBZO+1mww==","start":"2022/10/06 10:45","end":"2022/10/06 12:30"},{"domElements":["rsCalendar_5_0"],"id":"4560CS3/JXQIM","visible":true,"subject":"Chemistry\\u003cbr /\\u003eEwen Mclaughlin","timeZoneID":"","description":"(SB22) 13:00-14:30","toolTip":"Chemistry\\u003cbr /\\u003eEwen Mclaughlin","recurrenceState":0,"internalID":"/wEFDTQ1NjBDUzMvSlhRSU1T/luKZkBZqvXXDu3GSyhONOS5b+X4F7ls0lDNS8/nng==","start":"2022/10/06 13:00","end":"2022/10/06 14:30"},{"domElements":["rsCalendar_6_0"],"id":"4563R1K/VKSQO","visible":true,"subject":"Chemistry\\u003cbr /\\u003eEwen Mclaughlin","timeZoneID":"","description":"(SB22) 12:00-13:00","toolTip":"Chemistry\\u003cbr /\\u003eEwen Mclaughlin","recurrenceState":0,"internalID":"/wEFDTQ1NjNSMUsvVktTUU8xpLzoJr8i0+fsFV7TIElDq3ITys9W9r+tCq8RSELNaA==","start":"2022/10/07 12:00","end":"2022/10/07 13:00"},{"domElements":["rsCalendar_7_0"],"id":"4564FJT/PETCS","visible":true,"subject":"Biology\\u003cbr /\\u003eJeremy Lewis","timeZoneID":"","description":"(SB24) 13:00-14:00","toolTip":"Biology\\u003cbr /\\u003eJeremy Lewis","recurrenceState":0,"internalID":"/wEFDTQ1NjRGSlQvUEVUQ1MyTZq+0dkmlHTXGzEUzdS9w2pvVaKU1T4HpY7WNChcWQ==","start":"2022/10/07 13:00","end":"2022/10/07 14:00"},{"domElements":["rsCalendar_8_0"],"id":"4561YBS/CGQKW","visible":true,"subject":"Project\\u003cbr /\\u003eEwen Mclaughlin","timeZoneID":"","description":"(SB22) 14:15-15:15","toolTip":"Project\\u003cbr /\\u003eEwen Mclaughlin","recurrenceState":0,"internalID":"/wEFDTQ1NjFZQlMvQ0dRS1dLCIcfcoMb5sJoQ48O5jAbTin7W3yyokRtHvBHDrfDMA==","start":"2022/10/07 14:15","end":"2022/10/07 15:15"}],"attributes":{},"clientStateFieldID":"rsCalendar_ClientState","dayViewSettings":{"dayStartTime":28800000,"dayEndTime":64800000,"workDayStartTime":28800000,"workDayEndTime":61200000,"headerDateFormat":"dd, MMMM yyyy"},"firstDayOfWeek":1,"firstDayStart":"2022/10/03 09:00","lastDayOfWeek":5,"localization":{"AllDay":"all day","Show24Hours":"Show 24 hours...","ShowBusinessHours":"Show business hours...","Save":"Save","Cancel":"Cancel","Delete":"Delete","ShowAdvancedForm":"Options","ShowMore":"more...","AdvancedReset":"reset exceptions","AdvancedWorking":"Working...","AdvancedDone":"Done","AdvancedNewAppointment":"New Appointment","AdvancedEditAppointment":"Edit Appointment","AdvancedClose":"Close","Reminder":"Reminder","Reminders":"Reminders","ConfirmRecurrenceEditTitle":"Editing a recurring appointment","ConfirmRecurrenceEditOccurrence":"Edit only this occurrence.","ConfirmRecurrenceEditSeries":"Edit the series.","ConfirmRecurrenceResizeTitle":"Resizing a recurring appointment","ConfirmRecurrenceResizeOccurrence":"Resize only this occurrence.","ConfirmRecurrenceResizeSeries":"Resize the series.","ConfirmRecurrenceDeleteTitle":"Deleting a recurring appointment","ConfirmRecurrenceDeleteOccurrence":"Delete only this occurrence.","ConfirmRecurrenceDeleteSeries":"Delete the series.","ConfirmDeleteTitle":"Confirm delete","ConfirmDeleteText":"Are you sure you want to delete this appointment?","ConfirmRecurrenceMoveTitle":"Moving a recurring appointment","ConfirmRecurrenceMoveOccurrence":"Move only this occurrence.","ConfirmRecurrenceMoveSeries":"Move the series.","ConfirmOK":"OK","ConfirmCancel":"Cancel","ConfirmResetExceptionsTitle":"Confirm reset exceptions","ConfirmResetExceptionsText":"Do you want to delete all existing recurrence exceptions?","ContextMenuEdit":"Edit","ContextMenuDelete":"Delete","ContextMenuAddAppointment":"New Appointment","ContextMenuAddRecurringAppointment":"New Recurring Appointment","ContextMenuGoToToday":"Go to today"},"multiDayViewSettings":{"dayStartTime":28800000,"dayEndTime":64800000,"workDayStartTime":28800000,"workDayEndTime":61200000},"postBackReference":"__doPostBack(\u0027rsCalendar\u0027,\u0027arguments\u0027)","readOnly":true,"rowHeight":"30px","selectedDate":"2022/10/05 00:00","selectedView":1,"shouldPostbackOnClick":false,"showAllDayRow":false,"weekViewSettings":{"dayStartTime":32400000,"dayEndTime":75600000,"workDayStartTime":28800000,"workDayEndTime":61200000,"headerDateFormat":"dd, MMMM yyyy"}}